[{"time":"1981-09-22","open":0.02,"high":0.02,"low":0.02,"close":0.02,"volume":7449469},{"time":"1981-09-23","open":0.02,"high":0.02,"low":0.02,"close":0.02,"volume":7381125},{"time":"1981-09-24","open":0.02,"high":0.02,"low":0.02,"close":0.02,"volume":5091609},{"time":"1981-09-25","open":0.02,"high":0.02,"low":0.02,"close":0.02,"volume":7312781},{"time":"1981-09-28","open":0.02,"high":0.02,"low":0.02,"close":0.02,"volume":5809219},{"time":"1981-09-29","open":0.02,"high":0.02,"low":0.02,"close":0.02,"volume":3963938},{"time":"1981-09-30","open":0.02,"high":0.02,"low":0.02,"close":0.02,"volume":5262469},{"time":"1981-10-01","open":0.02,"high":0.02,"low":0.02,"close":0.02,"volume":4374000},{"time":"1981-10-02","open":0.02,"high":0.02,"low":0.02,"close":0.02,"volume":3485531},{"time":"1981-10-05","open":0.02,"high":0.02,"low":0.02,"close":0.02,"volume":1776938},{"time":"1981-10-06","open":0.02,"high":0.02,"low":0.02,"close":0.02,"volume":2528719},{"time":"1981-10-07","open":0.02,"high":0.02,"low":0.02,"close":0.02,"volume":4203141},{"time":"1981-10-08","open":0.02,"high":0.02,"low":0.02,"close":0.02,"volume":136688},{"time":"1981-10-09","open":0.02,"high":0.02,"low":0.02,"close":0.02,"volume":5638359},{"time":"1981-10-12","open":0.02,"high":0.02,"low":0.02,"close":0.02,"volume":375891},{"time":"1981-10-13","open":0.02,"high":0.02,"low":0.02,"close":0.02,"volume":1161844},{"time":"1981-10-14","open":0.02,"high":0.02,"low":0.02,"close":0.02,"volume":375891},{"time":"1981-10-15","open":0.02,"high":0.02,"low":0.02,"close":0.02,"volume":3109641},{"time":"1981-10-16","open":0.02,"high":0.02,"low":0.02,"close":0.02,"volume":307547},{"time":"1981-10-19","open":0.02,"high":0.02,"low":0.02,"close":0.02,"volume":1230188},{"time":"1981-10-20","open":0.02,"high":0.02,"low":0.02,"close":0.02,"volume":1503563},{"time":"1981-10-21","open":0.02,"high":0.02,"low":0.02,"close":0.02,"volume":7107750},{"time":"1981-10-22","open":0.02,"high":0.02,"low":0.02,"close":0.02,"volume":6390141},{"time":"1981-10-23","open":0.02,"high":0.03,"low":0.02,"close":0.02,"volume":3929766},{"time":"1981-10-26","open":0.02,"high":0.03,"low":0.02,"close":0.02,"volume":4305656},{"time":"1981-10-27","open":0.02,"high":0.03,"low":0.02,"close":0.02,"volume":1264359},{"time":"1981-10-28","open":0.02,"high":0.03,"low":0.02,"close":0.02,"volume":3451359},{"time":"1981-10-29","open":0.02,"high":0.03,"low":0.02,"close":0.02,"volume":615094},{"time":"1981-10-30","open":0.02,"high":0.03,"low":0.02,"close":0.02,"volume":444234},{"time":"1981-11-02","open":0.03,"high":0.03,"low":0.03,"close":0.03,"volume":854297},{"time":"1981-11-03","open":0.03,"high":0.03,"low":0.03,"close":0.03,"volume":1093500},{"time":"1981-11-04","open":0.03,"high":0.03,"low":0.03,"close":0.03,"volume":1127672},{"time":"1981-11-05","open":0.03,"high":0.03,"low":0.03,"close":0.03,"volume":4271484},{"time":"1981-11-06","open":0.03,"high":0.03,"low":0.03,"close":0.03,"volume":136688},{"time":"1981-11-09","open":0.03,"high":0.03,"low":0.02,"close":0.02,"volume":4442344},{"time":"1981-11-10","open":0.02,"high":0.03,"low":0.02,"close":0.02,"volume":2802094},{"time":"1981-11-11","open":0.02,"high":0.03,"low":0.02,"close":0.02,"volume":375891},{"time":"1981-11-12","open":0.02,"high":0.03,"low":0.02,"close":0.02,"volume":683438},{"time":"1981-11-13","open":0.02,"high":0.03,"low":0.02,"close":0.02,"volume":307547},{"time":"1981-11-16","open":0.02,"high":0.03,"low":0.02,"close":0.02,"volume":2870438},{"time":"1981-11-17","open":0.03,"high":0.03,"low":0.03,"close":0.03,"volume":170859},{"time":"1981-11-18","open":0.03,"high":0.03,"low":0.03,"close":0.03,"volume":375891},{"time":"1981-11-19","open":0.03,"high":0.03,"low":0.03,"close":0.03,"volume":170859},{"time":"1981-11-20","open":0.03,"high":0.03,"low":0.03,"close":0.03,"volume":2665406},{"time":"1981-11-23","open":0.03,"high":0.03,"low":0.03,"close":0.03,"volume":922641},{"time":"1981-11-24","open":0.03,"high":0.03,"low":0.03,"close":0.03,"volume":341719},{"time":"1981-11-25","open":0.03,"high":0.03,"low":0.03,"close":0.03,"volume":205031},{"time":"1981-11-27","open":0.03,"high":0.03,"low":0.03,"close":0.03,"volume":170859},{"time":"1981-11-30","open":0.03,"high":0.03,"low":0.03,"close":0.03,"volume":102516},{"time":"1981-12-01","open":0.03,"high":0.03,"low":0.03,"close":0.03,"volume":170859},{"time":"1981-12-02","open":0.03,"high":0.03,"low":0.03,"close":0.03,"volume":375891},{"time":"1981-12-03","open":0.03,"high":0.03,"low":0.03,"close":0.03,"volume":1708594},{"time":"1981-12-04","open":0.03,"high":0.03,"low":0.03,"close":0.03,"volume":4784063},{"time":"1981-12-07","open":0.03,"high":0.03,"low":0.03,"close":0.03,"volume":3963938},{"time":"1981-12-08","open":0.03,"high":0.03,"low":0.03,"close":0.03,"volume":2870438},{"time":"1981-12-09","open":0.03,"high":0.03,"low":0.03,"close":0.03,"volume":1230188},{"time":"1981-12-10","open":0.03,"high":0.03,"low":0.03,"close":0.03,"volume":751781},{"time":"1981-12-11","open":0.03,"high":0.03,"low":0.03,"close":0.03,"volume":273375},{"time":"1981-12-14","open":0.03,"high":0.03,"low":0.03,"close":0.03,"volume":1674422},{"time":"1981-12-15","open":0.03,"high":0.03,"low":0.03,"close":0.03,"volume":2870438},{"time":"1981-12-16","open":0.03,"high":0.03,"low":0.03,"close":0.03,"volume":170859},{"time":"1981-12-17","open":0.03,"high":0.03,"low":0.03,"close":0.03,"volume":1913625},{"time":"1981-12-18","open":0.03,"high":0.03,"low":0.03,"close":0.03,"volume":546750},{"time":"1981-12-21","open":0.03,"high":0.03,"low":0.03,"close":0.03,"volume":854297},{"time":"1981-12-22","open":0.03,"high":0.03,"low":0.03,"close":0.03,"volume":1401047},{"time":"1981-12-23","open":0.03,"high":0.03,"low":0.03,"close":0.03,"volume":1161844},{"time":"1981-12-24","open":0.03,"high":0.03,"low":0.03,"close":0.03,"volume":1776938},{"time":"1981-12-28","open":0.03,"high":0.03,"low":0.03,"close":0.03,"volume":444234},{"time":"1981-12-29","open":0.03,"high":0.03,"low":0.03,"close":0.03,"volume":410063},{"time":"1981-12-30","open":0.03,"high":0.03,"low":0.03,"close":0.03,"volume":444234},{"time":"1981-12-31","open":0.03,"high":0.03,"low":0.03,"close":0.03,"volume":273375},{"time":"1982-01-04","open":0.03,"high":0.03,"low":0.03,"close":0.03,"volume":136688},{"time":"1982-01-05","open":0.03,"high":0.03,"low":0.03,"close":0.03,"volume":410063},{"time":"1982-01-06","open":0.03,"high":0.03,"low":0.03,"close":0.03,"volume":307547},{"time":"1982-01-07","open":0.03,"high":0.03,"low":0.03,"close":0.03,"volume":3075469},{"time":"1982-01-08","open":0.03,"high":0.03,"low":0.03,"close":0.03,"volume":410063},{"time":"1982-01-11","open":0.03,"high":0.03,"low":0.03,"close":0.03,"volume":375891},{"time":"1982-01-12","open":0.03,"high":0.03,"low":0.03,"close":0.03,"volume":307547},{"time":"1982-01-13","open":0.03,"high":0.03,"low":0.03,"close":0.03,"volume":34172},{"time":"1982-01-14","open":0.03,"high":0.03,"low":0.03,"close":0.03,"volume":68344},{"time":"1982-01-15","open":0.03,"high":0.03,"low":0.03,"close":0.03,"volume":273375},{"time":"1982-01-18","open":0.03,"high":0.03,"low":0.03,"close":0.03,"volume":170859},{"time":"1982-01-19","open":0.03,"high":0.03,"low":0.03,"close":0.03,"volume":1161844},{"time":"1982-01-20","open":0.03,"high":0.03,"low":0.03,"close":0.03,"volume":182250},{"time":"1982-01-21","open":0.03,"high":0.03,"low":0.03,"close":0.03,"volume":2528719},{"time":"1982-01-22","open":0.03,"high":0.03,"low":0.03,"close":0.03,"volume":637875},{"time":"1982-01-25","open":0.03,"high":0.03,"low":0.03,"close":0.03,"volume":797344},{"time":"1982-01-26","open":0.03,"high":0.03,"low":0.03,"close":0.03,"volume":455625},{"time":"1982-01-27","open":0.03,"high":0.03,"low":0.03,"close":0.03,"volume":1344094},{"time":"1982-01-28","open":0.03,"high":0.03,"low":0.03,"close":0.03,"volume":432844},{"time":"1982-01-29","open":0.03,"high":0.03,"low":0.03,"close":0.03,"volume":205031},{"time":"1982-02-01","open":0.03,"high":0.03,"low":0.03,"close":0.03,"volume":91125},{"time":"1982-02-02","open":0.03,"high":0.03,"low":0.03,"close":0.03,"volume":820125},{"time":"1982-02-03","open":0.03,"high":0.03,"low":0.03,"close":0.03,"volume":911250},{"time":"1982-02-04","open":0.03,"high":0.03,"low":0.03,"close":0.03,"volume":182250},{"time":"1982-02-05","open":0.03,"high":0.03,"low":0.03,"close":0.03,"volume":1344094},{"time":"1982-02-08","open":0.03,"high":0.03,"low":0.03,"close":0.03,"volume":1093500},{"time":"1982-02-09","open":0.03,"high":0.03,"low":0.03,"close":0.03,"volume":136688},{"time":"1982-02-10","open":0.03,"high":0.03,"low":0.03,"close":0.03,"volume":751781},{"time":"1982-02-11","open":0.03,"high":0.03,"low":0.03,"close":0.03,"volume":387281},{"time":"1982-02-12","open":0.03,"high":0.03,"low":0.03,"close":0.03,"volume":546750},{"time":"1982-02-16","open":0.03,"high":0.03,"low":0.03,"close":0.03,"volume":546750},{"time":"1982-02-17","open":0.03,"high":0.03,"low":0.03,"close":0.03,"volume":273375},{"time":"1982-02-18","open":0.03,"high":0.03,"low":0.03,"close":0.03,"volume":22781},{"time":"1982-02-19","open":0.03,"high":0.03,"low":0.03,"close":0.03,"volume":1458000},{"time":"1982-02-22","open":0.03,"high":0.03,"low":0.03,"close":0.03,"volume":455625},{"time":"1982-02-23","open":0.03,"high":0.03,"low":0.03,"close":0.03,"volume":615094},{"time":"1982-02-24","open":0.03,"high":0.03,"low":0.03,"close":0.03,"volume":273375},{"time":"1982-02-25","open":0.03,"high":0.03,"low":0.03,"close":0.03,"volume":364500},{"time":"1982-02-26","open":0.03,"high":0.03,"low":0.03,"close":0.03,"volume":364500},{"time":"1982-03-01","open":0.03,"high":0.03,"low":0.03,"close":0.03,"volume":820125},{"time":"1982-03-02","open":0.03,"high":0.03,"low":0.03,"close":0.03,"volume":22781},{"time":"1982-03-03","open":0.03,"high":0.03,"low":0.03,"close":0.03,"volume":68344},{"time":"1982-03-04","open":0.03,"high":0.03,"low":0.03,"close":0.03,"volume":318938},{"time":"1982-03-05","open":0.03,"high":0.03,"low":0.03,"close":0.03,"volume":364500},{"time":"1982-03-08","open":0.03,"high":0.03,"low":0.03,"close":0.03,"volume":136688},{"time":"1982-03-09","open":0.03,"high":0.03,"low":0.03,"close":0.03,"volume":182250},{"time":"1982-03-10","open":0.03,"high":0.03,"low":0.03,"close":0.03,"volume":387281},{"time":"1982-03-11","open":0.03,"high":0.03,"low":0.03,"close":0.03,"volume":341719},{"time":"1982-03-12","open":0.03,"high":0.03,"low":0.03,"close":0.03,"volume":182250},{"time":"1982-03-15","open":0.03,"high":0.03,"low":0.03,"close":0.03,"volume":273375},{"time":"1982-03-16","open":0.03,"high":0.03,"low":0.03,"close":0.03,"volume":729000},{"time":"1982-03-17","open":0.03,"high":0.03,"low":0.03,"close":0.03,"volume":205031},{"time":"1982-03-18","open":0.03,"high":0.03,"low":0.03,"close":0.03,"volume":1184625},{"time":"1982-03-19","open":0.04,"high":0.04,"low":0.04,"close":0.04,"volume":820125},{"time":"1982-03-22","open":0.04,"high":0.04,"low":0.04,"close":0.04,"volume":1344094},{"time":"1982-03-23","open":0.04,"high":0.04,"low":0.04,"close":0.04,"volume":523969},{"time":"1982-03-24","open":0.04,"high":0.04,"low":0.04,"close":0.04,"volume":4100625},{"time":"1982-03-25","open":0.04,"high":0.04,"low":0.04,"close":0.04,"volume":2642625},{"time":"1982-03-26","open":0.04,"high":0.04,"low":0.04,"close":0.04,"volume":1981969},{"time":"1982-03-29","open":0.04,"high":0.04,"low":0.04,"close":0.04,"volume":3462750},{"time":"1982-03-30","open":0.04,"high":0.04,"low":0.04,"close":0.04,"volume":1116281},{"time":"1982-03-31","open":0.04,"high":0.04,"low":0.04,"close":0.04,"volume":1822500},{"time":"1982-04-01","open":0.04,"high":0.04,"low":0.04,"close":0.04,"volume":1161844},{"time":"1982-04-02","open":0.04,"high":0.04,"low":0.04,"close":0.04,"volume":569531},{"time":"1982-04-05","open":0.04,"high":0.04,"low":0.04,"close":0.04,"volume":2346469},{"time":"1982-04-06","open":0.04,"high":0.04,"low":0.04,"close":0.04,"volume":1776938},{"time":"1982-04-07","open":0.04,"high":0.04,"low":0.04,"close":0.04,"volume":2073094},{"time":"1982-04-08","open":0.04,"high":0.04,"low":0.04,"close":0.04,"volume":1252969},{"time":"1982-04-12","open":0.04,"high":0.04,"low":0.04,"close":0.04,"volume":523969},{"time":"1982-04-13","open":0.04,"high":0.04,"low":0.04,"close":0.04,"volume":546750},{"time":"1982-04-14","open":0.04,"high":0.04,"low":0.04,"close":0.04,"volume":1549125},{"time":"1982-04-15","open":0.04,"high":0.04,"low":0.04,"close":0.04,"volume":1184625},{"time":"1982-04-16","open":0.04,"high":0.04,"low":0.04,"close":0.04,"volume":4168969},{"time":"1982-04-19","open":0.04,"high":0.04,"low":0.04,"close":0.04,"volume":729000},{"time":"1982-04-20","open":0.04,"high":0.04,"low":0.04,"close":0.04,"volume":3371625},{"time":"1982-04-21","open":0.04,"high":0.04,"low":0.04,"close":0.04,"volume":250594},{"time":"1982-04-22","open":0.04,"high":0.04,"low":0.04,"close":0.04,"volume":1708594},{"time":"1982-04-23","open":0.04,"high":0.04,"low":0.04,"close":0.04,"volume":2278125},{"time":"1982-04-26","open":0.04,"high":0.04,"low":0.04,"close":0.04,"volume":523969},{"time":"1982-04-27","open":0.04,"high":0.04,"low":0.04,"close":0.04,"volume":318938},{"time":"1982-04-28","open":0.04,"high":0.04,"low":0.04,"close":0.04,"volume":729000},{"time":"1982-04-29","open":0.04,"high":0.04,"low":0.04,"close":0.04,"volume":3052688},{"time":"1982-04-30","open":0.04,"high":0.04,"low":0.04,"close":0.04,"volume":2437594},{"time":"1982-05-03","open":0.03,"high":0.03,"low":0.03,"close":0.03,"volume":2642625},{"time":"1982-05-04","open":0.03,"high":0.03,"low":0.03,"close":0.03,"volume":40095000},{"time":"1982-05-05","open":0.03,"high":0.04,"low":0.03,"close":0.03,"volume":24216469},{"time":"1982-05-06","open":0.04,"high":0.04,"low":0.04,"close":0.04,"volume":6902719},{"time":"1982-05-07","open":0.04,"high":0.04,"low":0.04,"close":0.04,"volume":4168969},{"time":"1982-05-10","open":0.04,"high":0.04,"low":0.04,"close":0.04,"volume":7130531},{"time":"1982-05-11","open":0.04,"high":0.04,"low":0.04,"close":0.04,"volume":5540400},{"time":"1982-05-12","open":0.04,"high":0.04,"low":0.04,"close":0.04,"volume":1840725},{"time":"1982-05-13","open":0.04,"high":0.05,"low":0.04,"close":0.04,"volume":5667975},{"time":"1982-05-14","open":0.04,"high":0.04,"low":0.04,"close":0.04,"volume":1603800},{"time":"1982-05-17","open":0.04,"high":0.05,"low":0.04,"close":0.04,"volume":16147350},{"time":"1982-05-18","open":0.04,"high":0.05,"low":0.04,"close":0.04,"volume":1257525},{"time":"1982-05-19","open":0.05,"high":0.05,"low":0.05,"close":0.05,"volume":2150550},{"time":"1982-05-20","open":0.05,"high":0.05,"low":0.05,"close":0.05,"volume":2515050},{"time":"1982-05-21","open":0.05,"high":0.05,"low":0.05,"close":0.05,"volume":2970675},{"time":"1982-05-24","open":0.05,"high":0.05,"low":0.05,"close":0.05,"volume":1111725},{"time":"1982-05-25","open":0.05,"high":0.05,"low":0.05,"close":0.05,"volume":3007125},{"time":"1982-05-26","open":0.05,"high":0.05,"low":0.05,"close":0.05,"volume":7107750},{"time":"1982-05-27","open":0.05,"high":0.05,"low":0.05,"close":0.05,"volume":8474625},{"time":"1982-05-28","open":0.05,"high":0.05,"low":0.05,"close":0.05,"volume":6050700},{"time":"1982-06-01","open":0.05,"high":0.05,"low":0.05,"close":0.05,"volume":783675},{"time":"1982-06-02","open":0.05,"high":0.05,"low":0.05,"close":0.05,"volume":4884300},{"time":"1982-06-03","open":0.06,"high":0.06,"low":0.06,"close":0.06,"volume":4610925},{"time":"1982-06-04","open":0.06,"high":0.06,"low":0.06,"close":0.06,"volume":1549125},{"time":"1982-06-07","open":0.06,"high":0.06,"low":0.06,"close":0.06,"volume":2879550},{"time":"1982-06-08","open":0.06,"high":0.06,"low":0.06,"close":0.06,"volume":911250},{"time":"1982-06-09","open":0.06,"high":0.06,"low":0.06,"close":0.06,"volume":5868450},{"time":"1982-06-10","open":0.06,"high":0.06,"low":0.06,"close":0.06,"volume":11499975},{"time":"1982-06-11","open":0.06,"high":0.06,"low":0.06,"close":0.06,"volume":2624400},{"time":"1982-06-14","open":0.06,"high":0.06,"low":0.06,"close":0.06,"volume":1038825},{"time":"1982-06-15","open":0.06,"high":0.06,"low":0.06,"close":0.06,"volume":1530900},{"time":"1982-06-16","open":0.06,"high":0.06,"low":0.06,"close":0.06,"volume":4866075},{"time":"1982-06-17","open":0.06,"high":0.06,"low":0.06,"close":0.06,"volume":3225825},{"time":"1982-06-18","open":0.05,"high":0.05,"low":0.05,"close":0.05,"volume":2879550},{"time":"1982-06-21","open":0.05,"high":0.05,"low":0.05,"close":0.05,"volume":3717900},{"time":"1982-06-22","open":0.05,"high":0.05,"low":0.05,"close":0.05,"volume":1239300},{"time":"1982-06-23","open":0.06,"high":0.06,"low":0.06,"close":0.06,"volume":2897775},{"time":"1982-06-24","open":0.06,"high":0.06,"low":0.06,"close":0.06,"volume":2879550},{"time":"1982-06-25","open":0.06,"high":0.06,"low":0.06,"close":0.06,"volume":564975},{"time":"1982-06-28","open":0.06,"high":0.06,"low":0.06,"close":0.06,"volume":1840725},{"time":"1982-06-29","open":0.06,"high":0.06,"low":0.06,"close":0.06,"volume":3134700},{"time":"1982-06-30","open":0.06,"high":0.06,"low":0.06,"close":0.06,"volume":5011875},{"time":"1982-07-01","open":0.06,"high":0.06,"low":0.06,"close":0.06,"volume":2259900},{"time":"1982-07-02","open":0.06,"high":0.06,"low":0.06,"close":0.06,"volume":1494450},{"time":"1982-07-06","open":0.06,"high":0.06,"low":0.06,"close":0.06,"volume":747225},{"time":"1982-07-07","open":0.06,"high":0.06,"low":0.06,"close":0.06,"volume":1749600},{"time":"1982-07-08","open":0.06,"high":0.06,"low":0.06,"close":0.06,"volume":2697300},{"time":"1982-07-09","open":0.06,"high":0.06,"low":0.06,"close":0.06,"volume":1020600},{"time":"1982-07-12","open":0.06,"high":0.06,"low":0.06,"close":0.06,"volume":1385100},{"time":"1982-07-13","open":0.06,"high":0.06,"low":0.06,"close":0.06,"volume":838350},{"time":"1982-07-14","open":0.06,"high":0.06,"low":0.06,"close":0.06,"volume":109350},{"time":"1982-07-15","open":0.06,"high":0.06,"low":0.06,"close":0.06,"volume":2861325},{"time":"1982-07-16","open":0.06,"high":0.06,"low":0.06,"close":0.06,"volume":783675},{"time":"1982-07-19","open":0.06,"high":0.06,"low":0.06,"close":0.06,"volume":346275},{"time":"1982-07-20","open":0.06,"high":0.06,"low":0.06,"close":0.06,"volume":2697300},{"time":"1982-07-21","open":0.06,"high":0.06,"low":0.06,"close":0.06,"volume":4556250},{"time":"1982-07-22","open":0.06,"high":0.06,"low":0.06,"close":0.06,"volume":2606175},{"time":"1982-07-23","open":0.06,"high":0.06,"low":0.06,"close":0.06,"volume":13377150},{"time":"1982-07-26","open":0.06,"high":0.06,"low":0.06,"close":0.06,"volume":7927875},{"time":"1982-07-27","open":0.06,"high":0.06,"low":0.06,"close":0.06,"volume":2278125},{"time":"1982-07-28","open":0.06,"high":0.06,"low":0.06,"close":0.06,"volume":3171150},{"time":"1982-07-29","open":0.06,"high":0.06,"low":0.06,"close":0.06,"volume":1275750},{"time":"1982-07-30","open":0.06,"high":0.06,"low":0.06,"close":0.06,"volume":3790800},{"time":"1982-08-02","open":0.06,"high":0.06,"low":0.06,"close":0.06,"volume":1111725},{"time":"1982-08-03","open":0.06,"high":0.06,"low":0.06,"close":0.06,"volume":2861325},{"time":"1982-08-04","open":0.06,"high":0.06,"low":0.06,"close":0.06,"volume":2478600},{"time":"1982-08-05","open":0.06,"high":0.06,"low":0.06,"close":0.06,"volume":1804275},{"time":"1982-08-06","open":0.06,"high":0.06,"low":0.06,"close":0.06,"volume":4610925},{"time":"1982-08-09","open":0.06,"high":0.06,"low":0.06,"close":0.06,"volume":3116475},{"time":"1982-08-10","open":0.06,"high":0.06,"low":0.06,"close":0.06,"volume":1366875},{"time":"1982-08-11","open":0.06,"high":0.06,"low":0.06,"close":0.06,"volume":838350},{"time":"1982-08-12","open":0.06,"high":0.06,"low":0.06,"close":0.06,"volume":5267025},{"time":"1982-08-13","open":0.06,"high":0.06,"low":0.06,"close":0.06,"volume":2423925},{"time":"1982-08-16","open":0.06,"high":0.06,"low":0.06,"close":0.06,"volume":765450},{"time":"1982-08-17","open":0.06,"high":0.06,"low":0.06,"close":0.06,"volume":2077650},{"time":"1982-08-18","open":0.06,"high":0.06,"low":0.06,"close":0.06,"volume":3535650},{"time":"1982-08-19","open":0.06,"high":0.06,"low":0.06,"close":0.06,"volume":3353400},{"time":"1982-08-20","open":0.07,"high":0.07,"low":0.07,"close":0.07,"volume":10333575},{"time":"1982-08-23","open":0.07,"high":0.07,"low":0.07,"close":0.07,"volume":11499975},{"time":"1982-08-24","open":0.07,"high":0.07,"low":0.07,"close":0.07,"volume":8037225},{"time":"1982-08-25","open":0.08,"high":0.08,"low":0.08,"close":0.08,"volume":19664775},{"time":"1982-08-26","open":0.08,"high":0.08,"low":0.08,"close":0.08,"volume":11627550},{"time":"1982-08-27","open":0.08,"high":0.08,"low":0.08,"close":0.08,"volume":13304250},{"time":"1982-08-30","open":0.08,"high":0.08,"low":0.08,"close":0.08,"volume":4483350},{"time":"1982-08-31","open":0.08,"high":0.08,"low":0.08,"close":0.08,"volume":6415200},{"time":"1982-09-01","open":0.08,"high":0.08,"low":0.08,"close":0.08,"volume":4975425},{"time":"1982-09-02","open":0.08,"high":0.08,"low":0.08,"close":0.08,"volume":5795550},{"time":"1982-09-03","open":0.08,"high":0.08,"low":0.08,"close":0.08,"volume":3881925},{"time":"1982-09-07","open":0.08,"high":0.08,"low":0.08,"close":0.08,"volume":3517425},{"time":"1982-09-08","open":0.08,"high":0.08,"low":0.08,"close":0.08,"volume":5194125},{"time":"1982-09-09","open":0.08,"high":0.08,"low":0.08,"close":0.08,"volume":13231350},{"time":"1982-09-10","open":0.08,"high":0.08,"low":0.08,"close":0.08,"volume":5868450},{"time":"1982-09-13","open":0.08,"high":0.08,"low":0.08,"close":0.08,"volume":3098250},{"time":"1982-09-14","open":0.08,"high":0.08,"low":0.08,"close":0.08,"volume":7362900},{"time":"1982-09-15","open":0.08,"high":0.08,"low":0.08,"close":0.08,"volume":1731375},{"time":"1982-09-16","open":0.08,"high":0.08,"low":0.08,"close":0.08,"volume":5850225},{"time":"1982-09-17","open":0.08,"high":0.08,"low":0.08,"close":0.08,"volume":4173525},{"time":"1982-09-20","open":0.08,"high":0.08,"low":0.08,"close":0.08,"volume":3845475},{"time":"1982-09-21","open":0.08,"high":0.08,"low":0.08,"close":0.08,"volume":7946100},{"time":"1982-09-22","open":0.08,"high":0.08,"low":0.08,"close":0.08,"volume":7745625},{"time":"1982-09-23","open":0.08,"high":0.08,"low":0.08,"close":0.08,"volume":10479375},{"time":"1982-09-24","open":0.08,"high":0.08,"low":0.08,"close":0.08,"volume":2114100},{"time":"1982-09-27","open":0.08,"high":0.08,"low":0.08,"close":0.08,"volume":7053075},{"time":"1982-09-28","open":0.09,"high":0.09,"low":0.09,"close":0.09,"volume":6870825},{"time":"1982-09-29","open":0.09,"high":0.09,"low":0.09,"close":0.09,"volume":3553875},{"time":"1982-09-30","open":0.09,"high":0.09,"low":0.09,"close":0.09,"volume":2205225},{"time":"1982-10-01","open":0.09,"high":0.09,"low":0.09,"close":0.09,"volume":2004750},{"time":"1982-10-04","open":0.09,"high":0.09,"low":0.09,"close":0.09,"volume":3207600},{"time":"1982-10-05","open":0.09,"high":0.09,"low":0.09,"close":0.09,"volume":2314575},{"time":"1982-10-06","open":0.09,"high":0.09,"low":0.09,"close":0.09,"volume":7217100},{"time":"1982-10-07","open":0.1,"high":0.11,"low":0.1,"close":0.1,"volume":10661625},{"time":"1982-10-08","open":0.11,"high":0.11,"low":0.11,"close":0.11,"volume":11354175},{"time":"1982-10-11","open":0.11,"high":0.11,"low":0.11,"close":0.11,"volume":8164800},{"time":"1982-10-12","open":0.1,"high":0.1,"low":0.1,"close":0.1,"volume":12739275},{"time":"1982-10-13","open":0.1,"high":0.1,"low":0.1,"close":0.1,"volume":8401725},{"time":"1982-10-14","open":0.1,"high":0.1,"low":0.1,"close":0.1,"volume":2077650},{"time":"1982-10-15","open":0.1,"high":0.1,"low":0.1,"close":0.1,"volume":7490475},{"time":"1982-10-18","open":0.11,"high":0.11,"low":0.11,"close":0.11,"volume":2970675},{"time":"1982-10-19","open":0.11,"high":0.11,"low":0.11,"close":0.11,"volume":3590325},{"time":"1982-10-20","open":0.11,"high":0.11,"low":0.11,"close":0.11,"volume":3499200},{"time":"1982-10-21","open":0.11,"high":0.11,"low":0.11,"close":0.11,"volume":4465125},{"time":"1982-10-22","open":0.11,"high":0.11,"low":0.11,"close":0.11,"volume":4264650},{"time":"1982-10-25","open":0.1,"high":0.1,"low":0.1,"close":0.1,"volume":8128350},{"time":"1982-10-26","open":0.09,"high":0.09,"low":0.09,"close":0.09,"volume":14798700},{"time":"1982-10-27","open":0.1,"high":0.1,"low":0.1,"close":0.1,"volume":5267025},{"time":"1982-10-28","open":0.1,"high":0.1,"low":0.1,"close":0.1,"volume":4720275},{"time":"1982-10-29","open":0.1,"high":0.1,"low":0.1,"close":0.1,"volume":1603800},{"time":"1982-11-01","open":0.1,"high":0.1,"low":0.1,"close":0.1,"volume":765450},{"time":"1982-11-02","open":0.11,"high":0.11,"low":0.11,"close":0.11,"volume":2460375},{"time":"1982-11-03","open":0.11,"high":0.11,"low":0.11,"close":0.11,"volume":6542775},{"time":"1982-11-04","open":0.11,"high":0.11,"low":0.11,"close":0.11,"volume":5795550},{"time":"1982-11-05","open":0.11,"high":0.11,"low":0.11,"close":0.11,"volume":3298725},{"time":"1982-11-08","open":0.11,"high":0.11,"low":0.11,"close":0.11,"volume":729000},{"time":"1982-11-09","open":0.11,"high":0.11,"low":0.11,"close":0.11,"volume":1421550},{"time":"1982-11-10","open":0.11,"high":0.11,"low":0.11,"close":0.11,"volume":5996025},{"time":"1982-11-11","open":0.11,"high":0.11,"low":0.11,"close":0.11,"volume":2296350},{"time":"1982-11-12","open":0.11,"high":0.12,"low":0.11,"close":0.11,"volume":2970675},{"time":"1982-11-15","open":0.11,"high":0.12,"low":0.11,"close":0.11,"volume":1767825},{"time":"1982-11-16","open":0.12,"high":0.12,"low":0.12,"close":0.12,"volume":6324075},{"time":"1982-11-17","open":0.13,"high":0.13,"low":0.13,"close":0.13,"volume":6797925},{"time":"1982-11-18","open":0.14,"high":0.14,"low":0.14,"close":0.14,"volume":6469875},{"time":"1982-11-19","open":0.14,"high":0.14,"low":0.13,"close":0.13,"volume":6688575},{"time":"1982-11-22","open":0.12,"high":0.12,"low":0.12,"close":0.12,"volume":7089525},{"time":"1982-11-23","open":0.12,"high":0.12,"low":0.12,"close":0.12,"volume":3881925},{"time":"1982-11-24","open":0.13,"high":0.13,"low":0.13,"close":0.13,"volume":3262275},{"time":"1982-11-26","open":0.13,"high":0.13,"low":0.13,"close":0.13,"volume":637875},{"time":"1982-11-29","open":0.13,"high":0.13,"low":0.13,"close":0.13,"volume":1603800},{"time":"1982-11-30","open":0.13,"high":0.13,"low":0.13,"close":0.13,"volume":3152925},{"time":"1982-12-01","open":0.14,"high":0.15,"low":0.14,"close":0.14,"volume":6469875},{"time":"1982-12-02","open":0.14,"high":0.14,"low":0.14,"close":0.14,"volume":5011875},{"time":"1982-12-03","open":0.15,"high":0.15,"low":0.15,"close":0.15,"volume":4483350},{"time":"1982-12-06","open":0.15,"high":0.15,"low":0.14,"close":0.14,"volume":6123600},{"time":"1982-12-07","open":0.15,"high":0.15,"low":0.15,"close":0.15,"volume":3663225},{"time":"1982-12-08","open":0.16,"high":0.17,"low":0.16,"close":0.16,"volume":7636275},{"time":"1982-12-09","open":0.18,"high":0.18,"low":0.18,"close":0.18,"volume":8984925},{"time":"1982-12-10","open":0.16,"high":0.16,"low":0.16,"close":0.16,"volume":3462750},{"time":"1982-12-13","open":0.16,"high":0.16,"low":0.16,"close":0.16,"volume":1530900},{"time":"1982-12-14","open":0.14,"high":0.14,"low":0.14,"close":0.14,"volume":6551888},{"time":"1982-12-15","open":0.14,"high":0.14,"low":0.14,"close":0.14,"volume":18115650},{"time":"1982-12-16","open":0.14,"high":0.14,"low":0.13,"close":0.13,"volume":4328438},{"time":"1982-12-17","open":0.14,"high":0.15,"low":0.14,"close":0.14,"volume":2879550},{"time":"1982-12-20","open":0.15,"high":0.15,"low":0.15,"close":0.15,"volume":1858950},{"time":"1982-12-21","open":0.15,"high":0.15,"low":0.15,"close":0.15,"volume":4401338},{"time":"1982-12-22","open":0.15,"high":0.15,"low":0.15,"close":0.15,"volume":4446900},{"time":"1982-12-23","open":0.15,"high":0.15,"low":0.15,"close":0.15,"volume":2104988},{"time":"1982-12-27","open":0.15,"high":0.16,"low":0.15,"close":0.15,"volume":3307838},{"time":"1982-12-28","open":0.15,"high":0.15,"low":0.15,"close":0.15,"volume":1713150},{"time":"1982-12-29","open":0.15,"high":0.15,"low":0.15,"close":0.15,"volume":902138},{"time":"1982-12-30","open":0.15,"high":0.15,"low":0.15,"close":0.15,"volume":1366875}]